{
    "homepage": "https://gitextensions.github.io/",
    "version": "3.2.0.5976",
    "license": "GPL-3.0-only",
    "description": "Git Standalone UI Tool. Installs latest appveyor build of master branch",
    "notes": "Post install script will convert app to portable mode.",
    "url": "https://ci.appveyor.com/api/buildjobs/sf6w57y45r5twkow/artifacts/Setup/GitExtensions-Portable-3.2.0.5976.zip",
    "hash": "b2a231905defeff1113fd1d39353c7804fe32f68704a9ffdfedf5e5a2e1bcd7f",
    "bin": [
        [
            "GitExtensions\\GitExtensions.exe",
            "gite"
        ]
    ],
    "shortcuts": [
        [
            "GitExtensions\\GitExtensions.exe",
            "Git Extensions"
        ]
    ],
    "checkver": {
        "url": "https://ci.appveyor.com/api/projects/gitextensions/gitextensions/branch/master",
        "regex": "\"jobId\":\"(?<buildjob>.*?)\".*\"version\":\"(?<version>[\\d.]+)\""
    },
    "autoupdate": {
        "url": "https://ci.appveyor.com/api/buildjobs/$matchBuildjob/artifacts/Setup/GitExtensions-Portable-$version.zip"
    },
    "post_install": [
        "(Get-Content -path \"$dir\\GitExtensions\\GitExtensions.exe.config\" -Raw) -replace '(?ms)IsPortable(.*?)False', 'IsPortable$1True' | Set-Content -path \"$dir\\GitExtensions\\GitExtensions.exe.config\"",
        "Copy-Item \"$persist_dir\\GitExtensionsShellEx64.dll\" \"$dir\\GitExtensions\"",
        "Copy-Item \"$persist_dir\\GitExtensionsShellEx32.dll\" \"$dir\\GitExtensions\""
    ],
    "persist": [
        "GitExtensions\\GitExtensions.settings",
        "GitExtensions\\Images",
        "GitExtensions\\Recent"
    ]
}
